django_admin_extras/__init__.py
django_admin_extras/filters/__init__.py
django_admin_extras/filters/input_filter.py
django_admin_extras/helpers/__init__.py
django_admin_extras/helpers/custom_titled_filter.py
django_admin_extras/helpers/custom_view_field.py
django_admin_extras/templates/admin/input_filter.html
django_admin_extras-1.0.2.dist-info/LICENSE.txt
django_admin_extras-1.0.2.dist-info/METADATA
django_admin_extras-1.0.2.dist-info/WHEEL
django_admin_extras-1.0.2.dist-info/top_level.txt
django_admin_extras-1.0.2.dist-info/RECORD
