Metadata-Version: 2.1
Name: django-admin-extras
Version: 1.0.2
Summary: Extra features for django.contrib.admin
Home-page: https://github.com/artrey/django-admin-extras.git
Author: Alexander Ivanov
Author-email: oz.sasha.ivanov@gmail.com
License: MIT
Keywords: django admin filter
Platform: any
Classifier: Intended Audience :: Developers
Classifier: Topic :: Software Development :: Libraries
Classifier: Programming Language :: Python :: 3
Classifier: Programming Language :: Python :: 3.6
Classifier: Programming Language :: Python :: Implementation :: PyPy
Requires-Dist: django (>=2.0)
